{
    "emacs-overlay": {
        "branch": "master",
        "description": "Bleeding edge emacs overlay [maintainer=@adisbladis] ",
        "homepage": "",
        "owner": "nix-community",
        "repo": "emacs-overlay",
        "rev": "5827ccc137b1558e74e6bf73108577b0eb401c0e",
        "sha256": "0mxbaxynbmsmrh0ynwm1in9ifgiawmg5l74cbnwmbgbspbvr70fi",
        "type": "tarball",
        "url": "https://github.com/nix-community/emacs-overlay/archive/5827ccc137b1558e74e6bf73108577b0eb401c0e.tar.gz",
        "url_template": "https://github.com/<owner>/<repo>/archive/<rev>.tar.gz"
    },
    "nixpkgs-20.03": {
        "branch": "release-20.03",
        "description": "A read-only mirror of NixOS/nixpkgs tracking the released channels. Send issues and PRs to",
        "homepage": "https://github.com/NixOS/nixpkgs",
        "owner": "NixOS",
        "repo": "nixpkgs",
        "rev": "825c68c4ae72b5563ac63826795de25189fc274b",
        "sha256": "01n02n1mlwdcvbxp3lmh20341cx0k35bxq5138hjjrmaimmya16z",
        "type": "tarball",
        "url": "https://github.com/NixOS/nixpkgs/archive/825c68c4ae72b5563ac63826795de25189fc274b.tar.gz",
        "url_template": "https://github.com/<owner>/<repo>/archive/<rev>.tar.gz"
    }
}
